src/__init__.py
src/config.py
src/config_keyloader.py
src/constants.py
src/gemini_client.py
src/server.py
src/models/__init__.py
src/models/schemas.py
src/tools/__init__.py
src/tools/blend.py
src/tools/edit.py
src/tools/generate.py
src/tools/status.py
src/utils/__init__.py
src/utils/debug_tools.py
src/utils/file_manager.py
src/utils/image_handler.py
src/utils/prompt_optimizer.py
nanobanana_mcp-1.0.2.dist-info/METADATA
nanobanana_mcp-1.0.2.dist-info/WHEEL
nanobanana_mcp-1.0.2.dist-info/entry_points.txt
nanobanana_mcp-1.0.2.dist-info/top_level.txt
nanobanana_mcp-1.0.2.dist-info/RECORD
