Metadata-Version: 2.4
Name: nanobanana-mcp
Version: 1.0.2
Summary: Gemini 2.5 Flash Image MCP Server for Claude Code
Author-email: Claude Code Assistant <support@anthropic.com>
Maintainer-email: Claude Code Assistant <support@anthropic.com>
License: MIT
Project-URL: Homepage, https://github.com/anthropic/nanobanana-mcp
Project-URL: Repository, https://github.com/anthropic/nanobanana-mcp
Project-URL: Issues, https://github.com/anthropic/nanobanana-mcp/issues
Project-URL: Changelog, https://github.com/anthropic/nanobanana-mcp/blob/main/CHANGELOG.md
Project-URL: Documentation, https://github.com/anthropic/nanobanana-mcp/blob/main/CLAUDE.md
Keywords: mcp,gemini,image-generation,claude,ai,nanobanana
Classifier: Development Status :: 4 - Beta
Classifier: Intended Audience :: Developers
Classifier: License :: OSI Approved :: MIT License
Classifier: Operating System :: OS Independent
Classifier: Programming Language :: Python :: 3
Classifier: Programming Language :: Python :: 3.8
Classifier: Programming Language :: Python :: 3.9
Classifier: Programming Language :: Python :: 3.10
Classifier: Programming Language :: Python :: 3.11
Classifier: Programming Language :: Python :: 3.12
Classifier: Topic :: Software Development :: Libraries :: Python Modules
Classifier: Topic :: Scientific/Engineering :: Artificial Intelligence
Classifier: Topic :: Multimedia :: Graphics
Requires-Python: >=3.8
Requires-Dist: google-genai>=0.3.0
Requires-Dist: fastmcp>=0.1.0
Requires-Dist: pydantic>=2.0.0
Requires-Dist: httpx>=0.24.0
Requires-Dist: psutil>=5.9.0
Requires-Dist: pillow>=9.0.0
Requires-Dist: python-dotenv>=1.0.0
Requires-Dist: rich>=13.0.0
Requires-Dist: typer>=0.9.0
Provides-Extra: dev
Requires-Dist: pytest>=7.0.0; extra == "dev"
Requires-Dist: pytest-asyncio>=0.21.0; extra == "dev"
Requires-Dist: black>=23.0.0; extra == "dev"
Requires-Dist: isort>=5.12.0; extra == "dev"
Requires-Dist: flake8>=6.0.0; extra == "dev"
Requires-Dist: mypy>=1.0.0; extra == "dev"
Provides-Extra: test
Requires-Dist: pytest>=7.0.0; extra == "test"
Requires-Dist: pytest-asyncio>=0.21.0; extra == "test"
Requires-Dist: pytest-cov>=4.0.0; extra == "test"
Provides-Extra: docs
Requires-Dist: sphinx>=7.0.0; extra == "docs"
Requires-Dist: sphinx-rtd-theme>=1.3.0; extra == "docs"
